pystock_crawler/__init__.py
pystock_crawler/exporters.py
pystock_crawler/items.py
pystock_crawler/loaders.py
pystock_crawler/settings.py
pystock_crawler/throttle.py
pystock_crawler/utils.py
pystock_crawler/spiders/__init__.py
pystock_crawler/spiders/edgar.py
pystock_crawler/spiders/nasdaq.py
pystock_crawler/spiders/yahoo.py
pystock_crawler-0.8.2.data/scripts/pystock-crawler
pystock_crawler-0.8.2.dist-info/DESCRIPTION.rst
pystock_crawler-0.8.2.dist-info/METADATA
pystock_crawler-0.8.2.dist-info/metadata.json
pystock_crawler-0.8.2.dist-info/RECORD
pystock_crawler-0.8.2.dist-info/top_level.txt
pystock_crawler-0.8.2.dist-info/WHEEL
