Metadata-Version: 2.0
Name: pystock-crawler
Version: 0.8.2
Summary: Crawl and parse stock historical data
Home-page: https://github.com/eliangcs/pystock-crawler
Author: Chang-Hung Liang
Author-email: eliang.cs@gmail.com
License: MIT
Platform: UNKNOWN
Classifier: Development Status :: 3 - Alpha
Classifier: Environment :: Console
Classifier: Intended Audience :: Developers
Classifier: Intended Audience :: Financial and Insurance Industry
Classifier: License :: OSI Approved :: MIT License
Classifier: Operating System :: OS Independent
Classifier: Programming Language :: Python
Classifier: Programming Language :: Python :: 2.7
Classifier: Topic :: Internet :: WWW/HTTP
Classifier: Topic :: Office/Business :: Financial :: Investment
Classifier: Topic :: Software Development :: Libraries :: Python Modules
Requires-Dist: docopt (==0.6.2)
Requires-Dist: leveldb (==0.193)
Requires-Dist: Scrapy (==0.24.4)
Requires-Dist: service-identity (==1.0.0)
